.DS_Store
.gitignore
CHANGELOG.txt
LICENCE.txt
MANIFEST.in
README.md
README.txt
setup.py
test.py
allnumbers/__init__.py
convert_indian_numbers.egg-info/PKG-INFO
convert_indian_numbers.egg-info/SOURCES.txt
convert_indian_numbers.egg-info/dependency_links.txt
convert_indian_numbers.egg-info/top_level.txt
convert_numbers_hindi/__init__.py
numbershindi/__init__.py