Metadata-Version: 2.1
Name: convert-indian-numbers
Version: 0.5
Summary: Arabic Persian English Hindi Numbers is a Python library to convert numbers from-to Arabic, Indian Hindi, Persian and English.
Home-page: https://github.com/pranjal5215/convert_numbers
Author: Azwri
Author-email: pranjal5215@gmail.com
License: MIT
Keywords: Arabic Persian English Indian Hindi Numbers Python conversion numbers from-to Arabic,Indian Hindi,Persian and English
Platform: UNKNOWN
Classifier: Development Status :: 5 - Production/Stable
Classifier: Operating System :: OS Independent
Classifier: License :: OSI Approved :: MIT License
Classifier: Programming Language :: Python :: 3
License-File: LICENCE.txt
